[{"id_service":"10","service":"x","inbox_table":"xin","inbox_content":"xinmsg","inbox_date":"xindate","inbox_flag":"xinflag","inbox_sender":"xinsender","outbox_table":"xout","outbox_content":"xoutmsg","outbox_date":"xoutdate","outbox_flag":"xoutflag","outbox_recipient":"xoutrecp","char_pemisah":"#"},{"id_service":"15","service":"tx","inbox_table":"tin","inbox_content":"tin_msg","inbox_date":"tin_date","inbox_flag":"tin_flag","inbox_sender":"tin_sender","outbox_table":"tout","outbox_content":"tout_msg","outbox_date":"tout_date","outbox_flag":"tout_flag","outbox_recipient":"tout_recp","char_pemisah":"#"}]